slick/__init__.py
slick/__version__.py
slick/app.py
slick/bencode.py
slick/certificate.py
slick/connection.py
slick/discovery.py
slick/friend.py
slick/friend_list.py
slick/identity.py
slick/logger.py
slick/repl.py
slick/server.py
slick/tor.py
slick/util.py
slick_app-0.0.2.dist-info/METADATA
slick_app-0.0.2.dist-info/WHEEL
slick_app-0.0.2.dist-info/entry_points.txt
slick_app-0.0.2.dist-info/top_level.txt
slick_app-0.0.2.dist-info/RECORD
