Metadata-Version: 2.1
Name: slick-app
Version: 0.0.2
Summary: Easy to use secure file sending & chatting
Home-page: https://github.com/joshbuddy/slick
Author: joshbuddy
Author-email: joshbuddy@gmail.com
License: MIT
Platform: UNKNOWN
Classifier: License :: OSI Approved :: MIT License
Classifier: Programming Language :: Python
Classifier: Programming Language :: Python :: 3
Classifier: Programming Language :: Python :: 3.7
Classifier: Programming Language :: Python :: Implementation :: CPython
Classifier: Programming Language :: Python :: Implementation :: PyPy
Requires-Python: >=3.7.0
Requires-Dist: aiofile (==1.5.1)
Requires-Dist: aiofiles (==0.4.0)
Requires-Dist: aiohttp (==3.5.0)
Requires-Dist: aiohttp-socks (==0.2.1)
Requires-Dist: aiozeroconf (==0.1.8)
Requires-Dist: altgraph (==0.16.1)
Requires-Dist: ansicolors (==1.1.8)
Requires-Dist: appdirs (==1.4.3)
Requires-Dist: asn1crypto (==0.24.0)
Requires-Dist: async-timeout (==3.0.1)
Requires-Dist: attrs (==18.2.0)
Requires-Dist: black (==18.9b0)
Requires-Dist: certifi (==2018.10.15)
Requires-Dist: cffi (==1.7.0)
Requires-Dist: chardet (==3.0.4)
Requires-Dist: Click (==7.0)
Requires-Dist: crypto (==1.4.1)
Requires-Dist: cryptography (==2.4.2)
Requires-Dist: filetype (==1.0.1)
Requires-Dist: future (==0.17.1)
Requires-Dist: humanize (==0.5.1)
Requires-Dist: idna (==2.7)
Requires-Dist: ifaddr (==0.1.4)
Requires-Dist: ipaddress (==1.0.22)
Requires-Dist: macholib (==1.11)
Requires-Dist: multidict (==4.4.2)
Requires-Dist: Naked (==0.1.31)
Requires-Dist: names (==0.3.0)
Requires-Dist: netifaces (==0.10.7)
Requires-Dist: ordered-set (==3.0.2)
Requires-Dist: pefile (==2018.8.8)
Requires-Dist: prompt-toolkit (==2.0.5)
Requires-Dist: pycparser (==2.19)
Requires-Dist: PyNaCl (==1.3.0)
Requires-Dist: python-libmagic (==0.4.0)
Requires-Dist: PyYAML (==3.13)
Requires-Dist: requests (==2.20.0)
Requires-Dist: shellescape (==3.4.1)
Requires-Dist: six (==1.11.0)
Requires-Dist: stem (==1.6.0)
Requires-Dist: toml (==0.10.0)
Requires-Dist: tqdm (==4.28.1)
Requires-Dist: typed-bencode (==0.0.1)
Requires-Dist: urllib3 (==1.24)
Requires-Dist: wcwidth (==0.1.7)
Requires-Dist: yarl (==1.2.6)
